asyncnostic/__init__.py
asyncnostic/legacy.py
asyncnostic/main.py
asyncnostic-0.1.1.dist-info/LICENSE
asyncnostic-0.1.1.dist-info/WHEEL
asyncnostic-0.1.1.dist-info/METADATA
asyncnostic-0.1.1.dist-info/RECORD
