Metadata-Version: 2.1
Name: asyncnostic
Version: 0.1.1
Summary: simple way of using pytest with async unit tests
Author: Derek Yu
Author-email: derek-nis@hotmail.com
Classifier: Programming Language :: Python :: 2
Classifier: Programming Language :: Python :: 2.7
Classifier: Programming Language :: Python :: 3
Classifier: Programming Language :: Python :: 3.4
Classifier: Programming Language :: Python :: 3.5
Classifier: Programming Language :: Python :: 3.6
Classifier: Programming Language :: Python :: 3.7
Classifier: Programming Language :: Python :: 3.8
